{
  "kapha": {
    "precision": 1.0,
    "recall": 1.0,
    "f1-score": 1.0,
    "support": 37.0
  },
  "pitta": {
    "precision": 1.0,
    "recall": 1.0,
    "f1-score": 1.0,
    "support": 32.0
  },
  "vata": {
    "precision": 1.0,
    "recall": 1.0,
    "f1-score": 1.0,
    "support": 31.0
  },
  "accuracy": 1.0,
  "macro avg": {
    "precision": 1.0,
    "recall": 1.0,
    "f1-score": 1.0,
    "support": 100.0
  },
  "weighted avg": {
    "precision": 1.0,
    "recall": 1.0,
    "f1-score": 1.0,
    "support": 100.0
  }
}